serato_usb_export/__init__.py
serato_usb_export/usb_export.py
serato_usb_export-1.1.1.dist-info/METADATA
serato_usb_export-1.1.1.dist-info/WHEEL
serato_usb_export-1.1.1.dist-info/entry_points.txt
serato_usb_export-1.1.1.dist-info/top_level.txt
serato_usb_export-1.1.1.dist-info/RECORD
