Metadata-Version: 2.4
Name: serato-usb-export
Version: 1.1.1
Summary: Better Serato USB export that beats Serato's sync by putting all files in 1 folder (without duplicates) and only copying changed files, unlike Serato's sync which takes forever and creates many duplicate file locations
Author-email: bvandercar-vt <bvandercar@outlook.com>
License-Expression: MIT
Project-URL: Homepage, https://pypi.org/project/serato-tools/
Project-URL: Repository, https://github.com/bvandercar-vt/serato-tools
Project-URL: Issues, https://github.com/bvandercar-vt/serato-tools/issues
Keywords: serato,serato usb,serato usb sync,serato usb export
Requires-Python: >=3.12
Requires-Dist: serato_tools>=3.6.2
